ttchat/__init__.py
ttchat/client.py
ttchat/encryption.py
ttchat/exceptions.py
ttchat/p2p.py
ttchat/server.py
ttchat-0.1.1.dist-info/LICENSE
ttchat-0.1.1.dist-info/METADATA
ttchat-0.1.1.dist-info/WHEEL
ttchat-0.1.1.dist-info/top_level.txt
ttchat-0.1.1.dist-info/RECORD
