Metadata-Version: 2.1
Name: ttchat
Version: 0.1.1
Summary: RSA-encrypted chat software written in Python.
Home-page: https://github.com/MysteryBlokHed/ttchat
Author: Adam Thompson-Sharpe
Author-email: adamthompsonsharpe@gmail.com
License: UNKNOWN
Platform: UNKNOWN
Classifier: Programming Language :: Python :: 3.6
Classifier: License :: OSI Approved :: MIT License
Classifier: Operating System :: OS Independent
Requires-Python: >=3.6
Requires-Dist: cryptography (>=2.8)
